todoist_service/consts.py
todoist_service/db.py
todoist_service/server/authorization/__init__.py
todoist_service/server/authorization/authorization.py
todoist_service/server/authorization/consts.py
todoist_service/server/authorization/registration.py
todoist_service/todoist_wrapper/__init__.py
todoist_service/todoist_wrapper/consts.py
todoist_service/todoist_wrapper/mock_todoist_wrapper.py
todoist_service/todoist_wrapper/todoist_api_wrapper.py
todoist_service/todoist_wrapper/todoist_wrapper.py
todoist_service-1.4.dist-info/METADATA
todoist_service-1.4.dist-info/WHEEL
todoist_service-1.4.dist-info/top_level.txt
todoist_service-1.4.dist-info/RECORD
