Metadata-Version: 2.1
Name: todoist-service
Version: 1.4
Summary: Provide framework for Todoist 3rd party services
Home-page: https://github.com/rosenpin/todoist-service
Author: Tomer Rosenfeld
Author-email: mail@tomerrosenfeld.com
License: Unlicense
Classifier: Programming Language :: Python :: 3
Requires-Python: >=3.8
Requires-Dist: todoist-api-python
Requires-Dist: flask
Requires-Dist: tinydb
Requires-Dist: requests-oauthlib
